excel2sqlite/__init__.py
excel2sqlite/cli.py
excel2sqlite/functions.py
excel2sqlite-0.1.0.dist-info/entry_points.txt
excel2sqlite-0.1.0.dist-info/WHEEL
excel2sqlite-0.1.0.dist-info/METADATA
excel2sqlite-0.1.0.dist-info/RECORD
