Metadata-Version: 2.1
Name: excel2sqlite
Version: 0.1.0
Summary: 
Author: CD Clark III
Author-email: clifton.clark@gmail.com
Requires-Python: >=3.8,<4.0
Classifier: Programming Language :: Python :: 3
Classifier: Programming Language :: Python :: 3.8
Classifier: Programming Language :: Python :: 3.9
Classifier: Programming Language :: Python :: 3.10
Classifier: Programming Language :: Python :: 3.11
Requires-Dist: openpyxl (>=3.0.10,<4.0.0)
Requires-Dist: pandas (>=1.5.1,<2.0.0)
Requires-Dist: typer (>=0.7.0,<0.8.0)
